{"_class":"page","do_objectID":"99773500-3E9D-4099-A172-173C2060BB54","booleanOperation":-1,"exportOptions":{"_class":"exportOptions","exportFormats":[],"includedLayerIds":[],"layerOptions":0,"shouldTrim":false},"frame":{"_class":"rect","constrainProportions":false,"height":0,"width":0,"x":0,"y":0},"isFixedToViewport":false,"isFlippedHorizontal":false,"isFlippedVertical":false,"isLocked":false,"isVisible":true,"layerListExpandedType":0,"name":"组件","nameIsFixed":false,"resizingConstraint":63,"resizingType":0,"rotation":0,"shouldBreakMaskChain":false,"clippingMaskMode":0,"hasClippingMask":false,"style":{"_class":"style","endMarkerType":0,"miterLimit":10,"startMarkerType":0,"windingRule":1},"groupLayout":{"_class":"MSImmutableFreeformGroupLayout"},"hasClickThrough":true,"layers":[{"_class":"symbolMaster","do_objectID":"65376335-6F53-45DE-908B-DE899F1E622F","booleanOperation":-1,"exportOptions":{"_class":"exportOptions","exportFormats":[],"includedLayerIds":[],"layerOptions":0,"shouldTrim":false},"frame":{"_class":"rect","constrainProportions":false,"height":196,"width":316,"x":100,"y":0},"isFixedToViewport":false,"isFlippedHorizontal":false,"isFlippedVertical":false,"isLocked":false,"isVisible":true,"layerListExpandedType":0,"name":"mokuai ","nameIsFixed":false,"resizingConstraint":63,"resizingType":0,"rotation":0,"shouldBreakMaskChain":true,"clippingMaskMode":0,"hasClippingMask":false,"style":{"_class":"style","endMarkerType":0,"miterLimit":10,"startMarkerType":0,"windingRule":1},"groupLayout":{"_class":"MSImmutableFreeformGroupLayout"},"hasClickThrough":true,"layers":[{"_class":"rectangle","do_objectID":"0A25E0ED-CEAF-40C3-B9F6-CE9FF06E957A","booleanOperation":-1,"exportOptions":{"_class":"exportOptions","exportFormats":[],"includedLayerIds":[],"layerOptions":0,"shouldTrim":false},"frame":{"_class":"rect","constrainProportions":false,"height":196,"width":316,"x":0,"y":0},"isFixedToViewport":false,"isFlippedHorizontal":false,"isFlippedVertical":false,"isLocked":false,"isVisible":true,"layerListExpandedType":0,"name":"矩形","nameIsFixed":false,"resizingConstraint":63,"resizingType":0,"rotation":0,"shouldBreakMaskChain":false,"clippingMaskMode":0,"hasClippingMask":false,"style":{"_class":"style","borders":[{"_class":"border","isEnabled":true,"color":{"_class":"color","alpha":1,"blue":0.592,"green":0.592,"red":0.592},"fillType":0,"position":1,"thickness":1}],"endMarkerType":0,"fills":[{"_class":"fill","isEnabled":true,"color":{"_class":"color","alpha":1,"blue":0.847,"green":0.847,"red":0.847},"fillType":0,"noiseIndex":0,"noiseIntensity":0,"patternFillType":1,"patternTileScale":1}],"miterLimit":10,"startMarkerType":0,"windingRule":1},"edited":false,"isClosed":true,"pointRadiusBehaviour":1,"points":[{"_class":"curvePoint","cornerRadius":0,"curveFrom":"{0, 0}","curveMode":1,"curveTo":"{0, 0}","hasCurveFrom":false,"hasCurveTo":false,"point":"{0, 0}"},{"_class":"curvePoint","cornerRadius":0,"curveFrom":"{1, 0}","curveMode":1,"curveTo":"{1, 0}","hasCurveFrom":false,"hasCurveTo":false,"point":"{1, 0}"},{"_class":"curvePoint","cornerRadius":0,"curveFrom":"{1, 1}","curveMode":1,"curveTo":"{1, 1}","hasCurveFrom":false,"hasCurveTo":false,"point":"{1, 1}"},{"_class":"curvePoint","cornerRadius":0,"curveFrom":"{0, 1}","curveMode":1,"curveTo":"{0, 1}","hasCurveFrom":false,"hasCurveTo":false,"point":"{0, 1}"}],"fixedRadius":0,"hasConvertedToNewRoundCorners":true},{"_class":"text","do_objectID":"A27F6E84-61D1-4769-9FB9-A3E5446B337F","booleanOperation":-1,"exportOptions":{"_class":"exportOptions","exportFormats":[],"includedLayerIds":[],"layerOptions":0,"shouldTrim":false},"frame":{"_class":"rect","constrainProportions":false,"height":118,"width":277,"x":21,"y":19},"isFixedToViewport":false,"isFlippedHorizontal":false,"isFlippedVertical":false,"isLocked":false,"isVisible":true,"layerListExpandedType":0,"name":"nuhaohaoajosndasjdls","nameIsFixed":false,"resizingConstraint":63,"resizingType":0,"rotation":0,"shouldBreakMaskChain":false,"clippingMaskMode":0,"hasClippingMask":false,"style":{"_class":"style","endMarkerType":0,"miterLimit":10,"startMarkerType":0,"textStyle":{"_class":"textStyle","encodedAttributes":{"MSAttributedStringFontAttribute":{"_class":"fontDescriptor","attributes":{"name":"PingFangSC-Regular","size":24}},"MSAttributedStringColorAttribute":{"_class":"color","alpha":1,"blue":0,"green":0,"red":0},"textStyleVerticalAlignmentKey":0,"paragraphStyle":{"_class":"paragraphStyle"}},"verticalAlignment":0},"windingRule":1},"attributedString":{"_class":"attributedString","string":"nuhaohaoajosndasjdlskadksahdkjsahdkasgdjsagdjasgdjsagd","attributes":[{"_class":"stringAttribute","location":0,"length":54,"attributes":{"MSAttributedStringFontAttribute":{"_class":"fontDescriptor","attributes":{"name":"PingFangSC-Regular","size":24}},"MSAttributedStringColorAttribute":{"_class":"color","alpha":1,"blue":0,"green":0,"red":0},"textStyleVerticalAlignmentKey":0,"paragraphStyle":{"_class":"paragraphStyle"}}}]},"automaticallyDrawOnUnderlyingPath":false,"dontSynchroniseWithSymbol":false,"glyphBounds":"{{1, 7}, {270, 90}}","lineSpacingBehaviour":2,"textBehaviour":2},{"_class":"oval","do_objectID":"950C98C0-E764-479B-830D-87A0E59992A8","booleanOperation":-1,"exportOptions":{"_class":"exportOptions","exportFormats":[],"includedLayerIds":[],"layerOptions":0,"shouldTrim":false},"frame":{"_class":"rect","constrainProportions":true,"height":38,"width":38,"x":21,"y":149},"isFixedToViewport":false,"isFlippedHorizontal":false,"isFlippedVertical":false,"isLocked":false,"isVisible":true,"layerListExpandedType":0,"name":"椭圆形","nameIsFixed":false,"resizingConstraint":63,"resizingType":0,"rotation":0,"shouldBreakMaskChain":false,"clippingMaskMode":0,"hasClippingMask":false,"style":{"_class":"style","borders":[{"_class":"border","isEnabled":true,"color":{"_class":"color","alpha":1,"blue":0.592,"green":0.592,"red":0.592},"fillType":0,"position":0,"thickness":1}],"endMarkerType":0,"fills":[{"_class":"fill","isEnabled":true,"color":{"_class":"color","alpha":1,"blue":1,"green":1,"red":1},"fillType":0,"noiseIndex":0,"noiseIntensity":0,"patternFillType":1,"patternTileScale":1}],"miterLimit":10,"startMarkerType":0,"windingRule":1},"edited":false,"isClosed":true,"pointRadiusBehaviour":1,"points":[{"_class":"curvePoint","cornerRadius":0,"curveFrom":"{0.77614237490000004, 1}","curveMode":2,"curveTo":"{0.22385762510000001, 1}","hasCurveFrom":true,"hasCurveTo":true,"point":"{0.5, 1}"},{"_class":"curvePoint","cornerRadius":0,"curveFrom":"{1, 0.22385762510000001}","curveMode":2,"curveTo":"{1, 0.77614237490000004}","hasCurveFrom":true,"hasCurveTo":true,"point":"{1, 0.5}"},{"_class":"curvePoint","cornerRadius":0,"curveFrom":"{0.22385762510000001, 0}","curveMode":2,"curveTo":"{0.77614237490000004, 0}","hasCurveFrom":true,"hasCurveTo":true,"point":"{0.5, 0}"},{"_class":"curvePoint","cornerRadius":0,"curveFrom":"{0, 0.77614237490000004}","curveMode":2,"curveTo":"{0, 0.22385762510000001}","hasCurveFrom":true,"hasCurveTo":true,"point":"{0, 0.5}"}]},{"_class":"symbolInstance","do_objectID":"49CEAA15-80D8-46B0-9F28-AB8C83D80E6D","booleanOperation":-1,"exportOptions":{"_class":"exportOptions","exportFormats":[],"includedLayerIds":[],"layerOptions":0,"shouldTrim":false},"frame":{"_class":"rect","constrainProportions":false,"height":19,"width":19,"x":289,"y":162},"isFixedToViewport":false,"isFlippedHorizontal":false,"isFlippedVertical":false,"isLocked":false,"isVisible":true,"layerListExpandedType":0,"name":"2","nameIsFixed":false,"resizingConstraint":63,"resizingType":0,"rotation":0,"shouldBreakMaskChain":false,"clippingMaskMode":0,"hasClippingMask":false,"style":{"_class":"style","endMarkerType":0,"miterLimit":10,"startMarkerType":0,"windingRule":1},"horizontalSpacing":0,"overrideValues":[],"scale":1,"symbolID":"D25AE590-C9C3-416D-B29E-F67052026CD4","verticalSpacing":0}],"backgroundColor":{"_class":"color","alpha":1,"blue":1,"green":1,"red":1},"hasBackgroundColor":false,"horizontalRulerData":{"_class":"rulerData","base":0,"guides":[]},"includeBackgroundColorInExport":true,"includeInCloudUpload":true,"isFlowHome":false,"resizesContent":false,"verticalRulerData":{"_class":"rulerData","base":0,"guides":[]},"includeBackgroundColorInInstance":false,"symbolID":"E18D255E-A51C-456F-8318-42AA2E464515","changeIdentifier":49,"overrideProperties":[{"_class":"MSImmutableOverrideProperty","canOverride":true,"overrideName":"A27F6E84-61D1-4769-9FB9-A3E5446B337F_stringValue"},{"_class":"MSImmutableOverrideProperty","canOverride":true,"overrideName":"49CEAA15-80D8-46B0-9F28-AB8C83D80E6D_symbolID"}],"allowsOverrides":true},{"_class":"symbolMaster","do_objectID":"B0001879-F698-4D2F-A941-7F2BA3D76DAC","booleanOperation":-1,"exportOptions":{"_class":"exportOptions","exportFormats":[],"includedLayerIds":[],"layerOptions":0,"shouldTrim":false},"frame":{"_class":"rect","constrainProportions":false,"height":19,"width":19,"x":516,"y":119},"isFixedToViewport":false,"isFlippedHorizontal":false,"isFlippedVertical":false,"isLocked":false,"isVisible":true,"layerListExpandedType":0,"name":"2","nameIsFixed":false,"resizingConstraint":63,"resizingType":0,"rotation":0,"shouldBreakMaskChain":true,"clippingMaskMode":0,"hasClippingMask":false,"style":{"_class":"style","endMarkerType":0,"miterLimit":10,"startMarkerType":0,"windingRule":1},"groupLayout":{"_class":"MSImmutableFreeformGroupLayout"},"hasClickThrough":true,"layers":[{"_class":"oval","do_objectID":"C1A98D16-E396-4B30-8018-F42DDFB7BF60","booleanOperation":-1,"exportOptions":{"_class":"exportOptions","do_objectID":"1874FA3D-150F-44CD-8F2E-02882F35E8BF","exportFormats":[],"includedLayerIds":[],"layerOptions":0,"shouldTrim":false},"frame":{"_class":"rect","do_objectID":"7A843F7F-8360-462B-B20E-01E6A8BCBCFB","constrainProportions":true,"height":19,"width":19,"x":0,"y":0},"isFixedToViewport":false,"isFlippedHorizontal":false,"isFlippedVertical":false,"isLocked":false,"isVisible":true,"layerListExpandedType":0,"name":"椭圆形备份","nameIsFixed":false,"resizingConstraint":63,"resizingType":0,"rotation":0,"shouldBreakMaskChain":false,"clippingMaskMode":0,"hasClippingMask":false,"style":{"_class":"style","do_objectID":"B4B316B5-A360-4EBF-B880-53388D548EF0","borders":[{"_class":"border","isEnabled":false,"color":{"_class":"color","alpha":1,"blue":0.592,"green":0.592,"red":0.592},"fillType":0,"position":0,"thickness":1}],"endMarkerType":0,"fills":[{"_class":"fill","isEnabled":true,"color":{"_class":"color","alpha":1,"blue":0.4894245426829268,"green":0.4894245426829268,"red":1},"fillType":0,"noiseIndex":0,"noiseIntensity":0,"patternFillType":1,"patternTileScale":1}],"miterLimit":10,"startMarkerType":0,"windingRule":1},"edited":false,"isClosed":true,"pointRadiusBehaviour":1,"points":[{"_class":"curvePoint","cornerRadius":0,"curveFrom":"{0.77614237490000004, 1}","curveMode":2,"curveTo":"{0.22385762510000001, 1}","hasCurveFrom":true,"hasCurveTo":true,"point":"{0.5, 1}"},{"_class":"curvePoint","cornerRadius":0,"curveFrom":"{1, 0.22385762510000001}","curveMode":2,"curveTo":"{1, 0.77614237490000004}","hasCurveFrom":true,"hasCurveTo":true,"point":"{1, 0.5}"},{"_class":"curvePoint","cornerRadius":0,"curveFrom":"{0.22385762510000001, 0}","curveMode":2,"curveTo":"{0.77614237490000004, 0}","hasCurveFrom":true,"hasCurveTo":true,"point":"{0.5, 0}"},{"_class":"curvePoint","cornerRadius":0,"curveFrom":"{0, 0.77614237490000004}","curveMode":2,"curveTo":"{0, 0.22385762510000001}","hasCurveFrom":true,"hasCurveTo":true,"point":"{0, 0.5}"}]}],"backgroundColor":{"_class":"color","alpha":1,"blue":1,"green":1,"red":1},"hasBackgroundColor":false,"horizontalRulerData":{"_class":"rulerData","base":0,"guides":[]},"includeBackgroundColorInExport":true,"includeInCloudUpload":true,"isFlowHome":false,"resizesContent":false,"verticalRulerData":{"_class":"rulerData","base":0,"guides":[]},"includeBackgroundColorInInstance":false,"symbolID":"D25AE590-C9C3-416D-B29E-F67052026CD4","changeIdentifier":13,"overrideProperties":[],"allowsOverrides":true},{"_class":"symbolMaster","do_objectID":"6ACB099A-56B1-4E2B-8BE9-E880B7520E6E","booleanOperation":-1,"exportOptions":{"_class":"exportOptions","do_objectID":"AE7FBAAF-E9AE-48FB-892F-DEC79A1F13FE","exportFormats":[],"includedLayerIds":[],"layerOptions":0,"shouldTrim":false},"frame":{"_class":"rect","do_objectID":"A783D487-128A-4115-B115-6FC501145487","constrainProportions":false,"height":19,"width":19,"x":557,"y":119},"isFixedToViewport":false,"isFlippedHorizontal":false,"isFlippedVertical":false,"isLocked":false,"isVisible":true,"layerListExpandedType":0,"name":"3","nameIsFixed":true,"resizingConstraint":63,"resizingType":0,"rotation":0,"shouldBreakMaskChain":true,"clippingMaskMode":0,"hasClippingMask":false,"style":{"_class":"style","do_objectID":"0E3D2814-97C1-4016-ADC3-35EEC61A02AD","endMarkerType":0,"miterLimit":10,"startMarkerType":0,"windingRule":1},"groupLayout":{"_class":"MSImmutableFreeformGroupLayout","do_objectID":"E21A8143-B054-4518-AC3C-346A0A26BE73"},"hasClickThrough":true,"layers":[{"_class":"oval","do_objectID":"5F5E6E1D-25BE-4216-AE36-3E796C607AA3","booleanOperation":-1,"exportOptions":{"_class":"exportOptions","do_objectID":"D4CF32CF-0B9B-460C-BF03-24CA8FE64EBC","exportFormats":[],"includedLayerIds":[],"layerOptions":0,"shouldTrim":false},"frame":{"_class":"rect","do_objectID":"3CC432C6-A9D8-463D-B0AA-17ABB321C435","constrainProportions":true,"height":19,"width":19,"x":0,"y":0},"isFixedToViewport":false,"isFlippedHorizontal":false,"isFlippedVertical":false,"isLocked":false,"isVisible":true,"layerListExpandedType":0,"name":"椭圆形备份","nameIsFixed":false,"resizingConstraint":63,"resizingType":0,"rotation":0,"shouldBreakMaskChain":false,"clippingMaskMode":0,"hasClippingMask":false,"style":{"_class":"style","do_objectID":"CDB2A932-9624-476F-BC3E-19E9867AA53D","borders":[{"_class":"border","isEnabled":false,"color":{"_class":"color","alpha":1,"blue":0.592,"green":0.592,"red":0.592},"fillType":0,"position":0,"thickness":1}],"endMarkerType":0,"fills":[{"_class":"fill","isEnabled":true,"color":{"_class":"color","alpha":1,"blue":0.4894245426829268,"green":1,"red":0.5318237283867048},"fillType":0,"noiseIndex":0,"noiseIntensity":0,"patternFillType":1,"patternTileScale":1}],"miterLimit":10,"startMarkerType":0,"windingRule":1},"edited":false,"isClosed":true,"pointRadiusBehaviour":1,"points":[{"_class":"curvePoint","cornerRadius":0,"curveFrom":"{0.77614237490000004, 1}","curveMode":2,"curveTo":"{0.22385762510000001, 1}","hasCurveFrom":true,"hasCurveTo":true,"point":"{0.5, 1}"},{"_class":"curvePoint","cornerRadius":0,"curveFrom":"{1, 0.22385762510000001}","curveMode":2,"curveTo":"{1, 0.77614237490000004}","hasCurveFrom":true,"hasCurveTo":true,"point":"{1, 0.5}"},{"_class":"curvePoint","cornerRadius":0,"curveFrom":"{0.22385762510000001, 0}","curveMode":2,"curveTo":"{0.77614237490000004, 0}","hasCurveFrom":true,"hasCurveTo":true,"point":"{0.5, 0}"},{"_class":"curvePoint","cornerRadius":0,"curveFrom":"{0, 0.77614237490000004}","curveMode":2,"curveTo":"{0, 0.22385762510000001}","hasCurveFrom":true,"hasCurveTo":true,"point":"{0, 0.5}"}]}],"backgroundColor":{"_class":"color","do_objectID":"B4F947AC-414F-4A90-BF3C-97C6345CE28A","alpha":1,"blue":1,"green":1,"red":1},"hasBackgroundColor":false,"horizontalRulerData":{"_class":"rulerData","do_objectID":"7CF674FF-8B5B-4504-88F1-1974B451A781","base":0,"guides":[]},"includeBackgroundColorInExport":true,"includeInCloudUpload":true,"isFlowHome":false,"resizesContent":false,"verticalRulerData":{"_class":"rulerData","do_objectID":"BA4AF9AE-D415-480C-8358-917ADB98A621","base":0,"guides":[]},"includeBackgroundColorInInstance":false,"symbolID":"299C916A-A991-4B9F-97A3-B3D4072A8BFA","changeIdentifier":44,"overrideProperties":[],"allowsOverrides":true},{"_class":"symbolMaster","do_objectID":"872501D3-9E8A-4D23-813D-03BDA5DB9AE6","booleanOperation":-1,"exportOptions":{"_class":"exportOptions","do_objectID":"8DF599A9-8722-4CA5-BA6F-E6B3C26CD738","exportFormats":[],"includedLayerIds":[],"layerOptions":0,"shouldTrim":false},"frame":{"_class":"rect","do_objectID":"0D7EF80A-3F6F-4E3F-85B2-3AFA7EF60D94","constrainProportions":false,"height":19,"width":19,"x":598,"y":119},"isFixedToViewport":false,"isFlippedHorizontal":false,"isFlippedVertical":false,"isLocked":false,"isVisible":true,"layerListExpandedType":0,"name":"4","nameIsFixed":true,"resizingConstraint":63,"resizingType":0,"rotation":0,"shouldBreakMaskChain":true,"clippingMaskMode":0,"hasClippingMask":false,"style":{"_class":"style","do_objectID":"F4E50719-B4FC-44E8-AFAE-6168529383AF","endMarkerType":0,"miterLimit":10,"startMarkerType":0,"windingRule":1},"groupLayout":{"_class":"MSImmutableFreeformGroupLayout","do_objectID":"16D7FA21-FA6F-476F-BFD9-6CFDE1C88B08"},"hasClickThrough":true,"layers":[{"_class":"oval","do_objectID":"ED7D1088-F44C-4242-8A83-33B84691D348","booleanOperation":-1,"exportOptions":{"_class":"exportOptions","do_objectID":"C52E2098-784B-4AD4-ABF6-452551D4BA6F","exportFormats":[],"includedLayerIds":[],"layerOptions":0,"shouldTrim":false},"frame":{"_class":"rect","do_objectID":"B160A2F5-763F-4ECD-B826-DB19A27CE4AA","constrainProportions":true,"height":19,"width":19,"x":0,"y":0},"isFixedToViewport":false,"isFlippedHorizontal":false,"isFlippedVertical":false,"isLocked":false,"isVisible":true,"layerListExpandedType":0,"name":"椭圆形备份","nameIsFixed":false,"resizingConstraint":63,"resizingType":0,"rotation":0,"shouldBreakMaskChain":false,"clippingMaskMode":0,"hasClippingMask":false,"style":{"_class":"style","do_objectID":"98DC122E-9E4A-4EE9-94C2-D695A817BEF8","borders":[{"_class":"border","isEnabled":false,"color":{"_class":"color","alpha":1,"blue":0.592,"green":0.592,"red":0.592},"fillType":0,"position":0,"thickness":1}],"endMarkerType":0,"fills":[{"_class":"fill","isEnabled":true,"color":{"_class":"color","alpha":1,"blue":1,"green":0.7431780902798136,"red":0.4894245426829268},"fillType":0,"noiseIndex":0,"noiseIntensity":0,"patternFillType":1,"patternTileScale":1}],"miterLimit":10,"startMarkerType":0,"windingRule":1},"edited":false,"isClosed":true,"pointRadiusBehaviour":1,"points":[{"_class":"curvePoint","cornerRadius":0,"curveFrom":"{0.77614237490000004, 1}","curveMode":2,"curveTo":"{0.22385762510000001, 1}","hasCurveFrom":true,"hasCurveTo":true,"point":"{0.5, 1}"},{"_class":"curvePoint","cornerRadius":0,"curveFrom":"{1, 0.22385762510000001}","curveMode":2,"curveTo":"{1, 0.77614237490000004}","hasCurveFrom":true,"hasCurveTo":true,"point":"{1, 0.5}"},{"_class":"curvePoint","cornerRadius":0,"curveFrom":"{0.22385762510000001, 0}","curveMode":2,"curveTo":"{0.77614237490000004, 0}","hasCurveFrom":true,"hasCurveTo":true,"point":"{0.5, 0}"},{"_class":"curvePoint","cornerRadius":0,"curveFrom":"{0, 0.77614237490000004}","curveMode":2,"curveTo":"{0, 0.22385762510000001}","hasCurveFrom":true,"hasCurveTo":true,"point":"{0, 0.5}"}]}],"backgroundColor":{"_class":"color","do_objectID":"67A4A872-0058-4938-8636-CF140958EDAE","alpha":1,"blue":1,"green":1,"red":1},"hasBackgroundColor":false,"horizontalRulerData":{"_class":"rulerData","do_objectID":"7BDA35EA-431B-47A3-B32F-4DD536AA5D95","base":0,"guides":[]},"includeBackgroundColorInExport":true,"includeInCloudUpload":true,"isFlowHome":false,"resizesContent":false,"verticalRulerData":{"_class":"rulerData","do_objectID":"375CDC1E-A531-4207-8533-44C06DB0D427","base":0,"guides":[]},"includeBackgroundColorInInstance":false,"symbolID":"275E309A-0038-4667-AB86-370DD0A3A8C1","changeIdentifier":75,"overrideProperties":[],"allowsOverrides":true}],"horizontalRulerData":{"_class":"rulerData","base":-370,"guides":[]},"includeInCloudUpload":true,"verticalRulerData":{"_class":"rulerData","base":-361,"guides":[]}}